odoo/addons/partner_optional_commercial_partner/LICENSE
odoo/addons/partner_optional_commercial_partner/README.rst
odoo/addons/partner_optional_commercial_partner/__init__.py
odoo/addons/partner_optional_commercial_partner/__manifest__.py
odoo/addons/partner_optional_commercial_partner/images/screen.png
odoo/addons/partner_optional_commercial_partner/models/__init__.py
odoo/addons/partner_optional_commercial_partner/models/res_partner.py
odoo/addons/partner_optional_commercial_partner/readme/CONTRIBUTORS.md
odoo/addons/partner_optional_commercial_partner/readme/DESCRIPTION.md
odoo/addons/partner_optional_commercial_partner/readme/USAGE.md
odoo/addons/partner_optional_commercial_partner/static/description/icon.png
odoo/addons/partner_optional_commercial_partner/static/description/index.html
odoo/addons/partner_optional_commercial_partner/tests/TEST_INSTRUCTIONS.rst
odoo/addons/partner_optional_commercial_partner/views/res_partner.xml
odoo_addon_partner_optional_commercial_partner-18.0.1.0.0.dist-info/METADATA
odoo_addon_partner_optional_commercial_partner-18.0.1.0.0.dist-info/WHEEL
odoo_addon_partner_optional_commercial_partner-18.0.1.0.0.dist-info/top_level.txt
odoo_addon_partner_optional_commercial_partner-18.0.1.0.0.dist-info/RECORD
